docs/source/conf.py
jale/__init__.py
jale/__main__.py
jale/ale.py
jale/ale_gui.py
jale/assets/__init__.py
jale/assets/ascii_logo.py
jale/assets/examples.zip
jale/assets/examples/analysis_info.xlsx
jale/assets/examples/config.yml
jale/assets/examples/experiment_info.xlsx
jale/assets/mask/Grey10.nii
jale/assets/mask/__init__.py
jale/assets/ml_models/cFWE_model.xgb
jale/assets/ml_models/tfce_model.xgb
jale/assets/ml_models/vFWE_model.xgb
jale/core/__init__.py
jale/core/analyses/__init__.py
jale/core/analyses/balanced_contrast.py
jale/core/analyses/clustering.py
jale/core/analyses/contrast.py
jale/core/analyses/main_effect.py
jale/core/analyses/probabilistic.py
jale/core/analyses/roi.py
jale/core/utils/__init__.py
jale/core/utils/compile_experiments.py
jale/core/utils/compute.py
jale/core/utils/contribution.py
jale/core/utils/cutoff_prediction.py
jale/core/utils/folder_setup.py
jale/core/utils/hierarchical.py
jale/core/utils/input.py
jale/core/utils/kernel.py
jale/core/utils/kmedoids.py
jale/core/utils/logger.py
jale/core/utils/plot_and_save.py
jale/core/utils/tal2icbm_spm.py
jale/core/utils/template.py
jale/gui/__init__.py
jale/gui/add_analysis_window.py
jale/gui/analysis_table_frame.py
jale/gui/controller.py
jale/gui/dataset_table_frame.py
jale/gui/output_frame.py
jale/gui/output_log_frame.py
jale/gui/parameter_window.py
jale/gui/sidebar_frame.py
jale/gui/tooltip.py
jale/gui/fonts/fonts.py
jale-0.2.7.dist-info/licenses/LICENSE
tests/__init__.py
tests/test_compile_experiments.py
tests/test_compute.py
tests/test_contribution.py
tests/test_cutoff_prediction.py
tests/test_folder_setup.py
tests/test_input.py
tests/test_kernel.py
tests/test_plot_and_save.py
tests/test_tal2icbm.py
tests/test_template.py
tests/utils.py
jale-0.2.7.dist-info/METADATA
jale-0.2.7.dist-info/WHEEL
jale-0.2.7.dist-info/top_level.txt
jale-0.2.7.dist-info/RECORD
