Metadata-Version: 2.4
Name: jale
Version: 0.2.7
Summary: Package allowing users to run Activation Likelihood Estimation Meta-Analysis
Author-email: Lennart Frahm <l.frahm@mailbox.org>
License-Expression: MIT
Classifier: Programming Language :: Python :: 3
Classifier: Programming Language :: Python :: 3.9
Classifier: Programming Language :: Python :: 3.10
Classifier: Programming Language :: Python :: 3.11
Classifier: Programming Language :: Python :: 3.12
Classifier: Operating System :: OS Independent
Requires-Python: <3.13,>=3.9
License-File: LICENSE
Requires-Dist: customtkinter==5.2.2
Requires-Dist: joblib>=1.3.2
Requires-Dist: nibabel>=5.2.1
Requires-Dist: numpy==1.26.4
Requires-Dist: pandas>=2.0.3
Requires-Dist: PyYAML>=6.0.2
Requires-Dist: scipy>=1.10.1
Requires-Dist: xgboost>=2.1.2
Requires-Dist: openpyxl>=3.1.5
Requires-Dist: scikit-learn==1.5.2
Requires-Dist: scikit-learn-extra==0.3.0
Requires-Dist: matplotlib>=3.7.1
Requires-Dist: seaborn>=0.12.2
Requires-Dist: nilearn>=0.10.4
Requires-Dist: jsonschema>=4.17.3
Dynamic: license-file
